signalbus/__init__.py
signalbus/py.typed
signalbus-0.2.5.dist-info/METADATA
signalbus-0.2.5.dist-info/WHEEL
signalbus-0.2.5.dist-info/RECORD
