Metadata-Version: 2.1
Name: signalbus
Version: 0.2.5
Summary: Simple and small library to broadcast signals with typing support
Home-page: https://github.com/klen/signalbus
License: MIT
Keywords: signal,emit,events,broadcast
Author: Kirill Klenov
Author-email: horneds@gmail.com
Requires-Python: >=3.8,<4.0
Classifier: Development Status :: 5 - Production/Stable
Classifier: Intended Audience :: Developers
Classifier: License :: OSI Approved :: MIT License
Classifier: Operating System :: OS Independent
Classifier: Programming Language :: Python
Classifier: Programming Language :: Python :: 3
Classifier: Programming Language :: Python :: 3.8
Classifier: Programming Language :: Python :: 3.9
Classifier: Programming Language :: Python :: 3.10
Classifier: Programming Language :: Python :: 3.11
Classifier: Topic :: Software Development :: Libraries
Requires-Dist: typing-extensions ; python_version < "3.10"
